README.rst
setup.cfg
setup.py
dict_trie/__init__.py
dict_trie/dict_trie.py
dict_trie.egg-info/PKG-INFO
dict_trie.egg-info/SOURCES.txt
dict_trie.egg-info/dependency_links.txt
dict_trie.egg-info/top_level.txt