Metadata-Version: 1.1
Name: dict-trie
Version: 1.0.1
Summary: Trie implementation for approximate string matching.
Home-page: http://dict-trie.readthedocs.io/en/latest/
Author: Jeroen F.J. Laros
Author-email: J.F.J.Laros@lumc.nl
License: MIT
Keywords: bioinformatics
Platform: UNKNOWN
Classifier: Development Status :: 4 - Beta
Classifier: Intended Audience :: Science/Research
Classifier: Intended Audience :: Developers
Classifier: Operating System :: OS Independent
Classifier: Programming Language :: Python
Classifier: Topic :: Scientific/Engineering
